LICENSE
README.md
setup.py
src/Pyprofiling_pkg_ankit_bose.egg-info/PKG-INFO
src/Pyprofiling_pkg_ankit_bose.egg-info/SOURCES.txt
src/Pyprofiling_pkg_ankit_bose.egg-info/dependency_links.txt
src/Pyprofiling_pkg_ankit_bose.egg-info/top_level.txt
src/pyprofiling/__init__.py
src/pyprofiling/pyprofiling.py